pygroupexc.py
pygroupexc-0.1.0.dist-info/LICENSE
pygroupexc-0.1.0.dist-info/WHEEL
pygroupexc-0.1.0.dist-info/METADATA
pygroupexc-0.1.0.dist-info/RECORD
