Metadata-Version: 2.1
Name: pygroupexc
Version: 0.1.0
Summary: Library for giving similar exceptions the same identifier
License: BSD License
Author: Frantisek Jahoda
Author-email: frantisek.jahoda@gmail.com
Requires-Python: >=3.8,<4.0
Classifier: License :: Other/Proprietary License
Classifier: Programming Language :: Python :: 3
Classifier: Programming Language :: Python :: 3.8
Classifier: Programming Language :: Python :: 3.9
